cereale_sdk/__init__.py
cereale_sdk/client.py
cereale_app-0.1.1.dist-info/METADATA
cereale_app-0.1.1.dist-info/WHEEL
cereale_app-0.1.1.dist-info/top_level.txt
cereale_app-0.1.1.dist-info/RECORD
