Metadata-Version: 2.1
Name: cereale_app
Version: 0.1.1
Summary: Python SDK for Cereale.app API
Home-page: https://bursadecereale.com/
Author: krakiun
Author-email: info@cereale.app
Project-URL: Homepage, https://bursadecereale.com/
Project-URL: Developer, https://krakiun.com/
Classifier: Programming Language :: Python :: 3
Classifier: License :: OSI Approved :: MIT License
Classifier: Operating System :: OS Independent
Requires-Python: >=3.6
Requires-Dist: requests >=2.25.0
